Workbook

Sheet README
A1: AI Use Case Prioritization Workbook
A2: Generated: 2025-11-03 17:01:48
A4: How to Use:
A5: 1) Review 'ScoringModel' and adjust weights/parameters as needed.
A6: 2) Browse 'BusinessFunctions' to ensure full coverage in discovery workshops.
A7: 3) Use 'PrimitiveGuide' to map frictions to AI primitives.
A8: 4) Add your ideas to 'Backlog' (one row per use case).
A9: 5) The sheet computes Value, Time-to-Value, Effort normalization, Priority Score, and Rank.
A10: 6) Update token assumptions to estimate monthly tokens per use case.
A11: 7) See 'ExecutiveDashboard' for portfolio KPIs and charts.

Sheet StepByStep
A1: Step # | B1: Phase | C1: What to Do
A2: 1 | B2: Anchor to Strategy & Drivers | C2: Confirm enterprise strategy, OKRs, and the four business drivers (Grow Revenue, Reduce Cost, Increase Cash Flow, Decrease Risk). Define 3–5 strategic themes.
A3: 2 | B3: Inventory Business Functions | C3: List all functions and sub-functions (Sales, Marketing, Product, Ops, Supply Chain, Manufacturing, Finance, Accounting, HR, IT, Legal/Compliance, Customer Service, Facilities/EHS, R&D, Strategy, Procurement, Risk/Security, Data/Analytics, PMO).
A4: 3 | B4: Map Friction Points | C4: Run 60–90 min workshops per function. Capture top pains: delays, rework, errors, compliance gaps, handoffs, knowledge gaps, seasonal peaks, and low-value repetitive work.
A5: 4 | B5: Match to AI Primitives | C5: For each friction, match the best-fit AI primitive(s): Content Creation, Research & Information Retrieval (RIR), Coding Assistance, Data Analysis, Conversational Interfaces, Workflow Automation.
A6: 5 | B6: Define KPIs & Baselines | C6: Turn each friction into a measurable outcome: choose a primary KPI, document baseline, target, timeframe, and measurement method. Ensure traceability to a business driver.
A7: 6 | B7: Quantify Driver Impacts ($) | C7: Translate KPI deltas into yearly USD by driver: Revenue (uplift * margin), Cost (hours saved * loaded rate + waste reduced), Cash Flow (DSO/inventory days improvement * working capital), Risk (probability * impact reduction).
A8: 7 | B8: Estimate Effort & Time-to-Value | C8: Score effort from 1–5 using data readiness, integration complexity, change management, and governance. Estimate months to first measurable value (TTV).
A9: 8 | B9: Assess Probability of Success | C9: Estimate 0–1 based on data availability/quality, precedent within industry, stakeholder buy-in, and maturity of tooling.
A10: 9 | B10: Score & Prioritize | C10: Use weighted scoring (adjustable) to compute Value, Time-to-Value score, Effort normalization, and overall Priority Score (0–100).
A11: 10 | B11: Portfolio & Sequencing | C11: Apply constraints (budget, capacity, compliance). Balance quick wins vs. strategic platforms. Sequence pilots then scale-outs.
A12: 11 | B12: Pilot, Instrument, Verify | C12: Stand up a pilot with instrumentation. Verify KPI change with A/B or pre/post. Track adoption and operational run rate.
A13: 12 | B13: Scale & Govern | C13: Operationalize with runbooks, alerts, model/data governance, risk controls, and continuous improvement loops.

Sheet BusinessFunctions
A1: Function | B1: Sub-Function
A2: Corporate Strategy | B2: Planning
A3: Corporate Strategy | B3: M&A / Corp Dev
A4: Corporate Strategy | B4: Competitive Intel
A5: Corporate Strategy | B5: PMO
A6: Sales | B6: Lead Gen
A7: Sales | B7: Prospecting
A8: Sales | B8: Account Mgmt
A9: Sales | B9: Proposal/Bid
A10: Sales | B10: Forecasting
A11: Sales | B11: Pricing
A12: Marketing | B12: Campaigns
... A88: Data/Analytics/AI | B88: Model Governance

Sheet PrimitiveGuide
A1: AI Primitive | B1: What It Does | C1: Typical KPIs
A2: Content Creation | B2: Generate/rewrite documents, emails, bids, marketing assets, specs, SOPs. | C2: KPI examples: throughput, quality score, time to draft, win rate uplift.
A3: Research & Information Retrieval (RIR) | B3: Find and synthesize facts from internal/external corpora; policy Q&A; RAG. | C3: KPI examples: answer accuracy, time to answer, case resolution rate.
A4: Coding Assistance | B4: Code gen/refactor/tests/migration; guardrails & secure patterns. | C4: KPI examples: story points per sprint, defects escaped, lead time change.
A5: Data Analysis | B5: Anomaly detection, forecasting, clustering, ranking, optimization. | C5: KPI examples: forecast MAPE, downtime reduction, waste/scrap reduction.
A6: Conversational Interfaces | B6: Copilots for employees/customers: guided flows + tools + memory. | C6: KPI examples: CSAT, FCR, AHT, deflection, adoption/DAU/MAU.
A7: Workflow Automation | B7: Orchestration across apps/people; auto-triage, routing, approvals. | C7: KPI examples: cycle time, throughput, SLA attainment, rework rate.

Sheet ScoringModel
A1: Item | B1: Cell | C1: Value
A2: Driver Weights
A3: Revenue | B3: ScoringModel!C3 | C3: 0.25
A4: Cost | B4: ScoringModel!C4 | C4: 0.25
A5: CashFlow | B5: ScoringModel!C5 | C5: 0.25
A6: Risk | B6: ScoringModel!C6 | C6: 0.25
A8: Priority Weights
A9: ValueWeight | B9: ScoringModel!C9 | C9: 0.5
A10: PsuccessWeight | B10: ScoringModel!C10 | C10: 0.2
A11: AlignmentWeight | B11: ScoringModel!C11 | C11: 0.15
A12: TimeToValueWeight | B12: ScoringModel!C12 | C12: 0.1
A13: EffortWeight | B13: ScoringModel!C13 | C13: 0.05
A15: Parameters
A16: ValueNormalizerUSD | B16: ScoringModel!C16 | C16: 1000000
A17: MaxTTVMonths | B17: ScoringModel!C17 | C17: 12
A18: MinEffortScore | B18: ScoringModel!C18 | C18: 1
A19: MaxEffortScore | B19: ScoringModel!C19 | C19: 5

Sheet Use Cases
A1: ID | B1: UseCase | C1: Function | D1: SubFunction | E1: Primitives | F1: FrictionPoint | G1: RevBenefitUSD | H1: CostBenefitUSD | I1: CashFlowBenefitUSD | J1: RiskBenefitUSD | K1: Psuccess | L1: Alignment | M1: TTV_Months | N1: EffortScore | O1: ValueScore | P1: TimeToValueScore | Q1: EffortScoreNorm | R1: PriorityScore | S1: Rank | T1: PrimaryKPI | U1: Baseline | V1: Target | W1: KPI_Timeframe_Months | X1: UsersOrProcesses | Y1: PromptsPerUserPerDay | Z1: ToolCallsPerPrompt | AA1: AvgInputTokens | AB1: AvgProcessingTokens | AC1: AvgReasoningTokens | AD1: AvgOutputTokens | AE1: DaysPerMonth | AF1: MonthlyTokens_Est
A2: 1 | B2: Sales Proposal Generator | C2: Sales | D2: Proposal/Bid | E2: Content Creation, RIR, Conversational | F2: Slow, inconsistent proposals; low reuse; missed deadlines. | G2: 2500000 | H2: 300000 | I2: 0 | J2: 0 | K2: 0.75 | L2: 0.95 | M2: 3 | N2: 3 | O2: =MIN((G2*ScoringModel!$C$3+H2*ScoringModel!$C$4+I2*ScoringModel!$C$5+J2*ScoringModel!$C$6)/ScoringModel!$C$16,1) -> 0.7 | P2: =1-MIN(M2/ScoringModel!$C$17,1) -> 0.75 | Q2: =(N2-ScoringModel!$C$18)/(ScoringModel!$C$19-ScoringModel!$C$18) -> 0.5 | R2: =100*(ScoringModel!$C$9*O2+ScoringModel!$C$10*K2+ScoringModel!$C$11*L2+ScoringModel!$C$12*P2+ScoringModel!$C$13*(1-Q2)) -> 74.25 | S2: =_xlfn.RANK.EQ(R2,$R$2:$R$11,0) -> 1 | T2: Win rate (%) | U2: 20 | V2: 21 | W2: 6 | X2: 60 | Y2: 8 | Z2: 1.3 | AA2: 1200 | AB2: 1600 | AC2: 300 | AD2: 1000 | AE2: 22 | AF2: =X2*Y2*AE2*Z2*(AA2+AB2+AC2+AD2) -> 56284800
A3: 2 | B3: Helpdesk Copilot (IT/HR) | C3: IT | D3: Helpdesk | E3: Conversational, RIR, Workflow Automation | F3: High L1 volume and long resolution times; duplicate tickets. | G3: 0 | H3: 600000 | I3: 0 | J3: 100000 | K3: 0.85 | L3: 0.9 | M3: 2 | N3: 2 | O3: =MIN((G3*ScoringModel!$C$3+H3*ScoringModel!$C$4+I3*ScoringModel!$C$5+J3*ScoringModel!$C$6)/ScoringModel!$C$16,1) -> 0.175 | P3: =1-MIN(M3/ScoringModel!$C$17,1) -> 0.83333333 | Q3: =(N3-ScoringModel!$C$18)/(ScoringModel!$C$19-ScoringModel!$C$18) -> 0.25 | R3: =100*(ScoringModel!$C$9*O3+ScoringModel!$C$10*K3+ScoringModel!$C$11*L3+ScoringModel!$C$12*P3+ScoringModel!$C$13*(1-Q3)) -> 51.333333 | S3: =_xlfn.RANK.EQ(R3,$R$2:$R$11,0) -> 5 | T3: First contact resolution (%) | U3: 55 | V3: 70 | W3: 6 | X3: 400 | Y3: 1 | Z3: 1.2 | AA3: 300 | AB3: 700 | AC3: 150 | AD3: 250 | AE3: 22 | AF3: =X3*Y3*AE3*Z3*(AA3+AB3+AC3+AD3) -> 14784000
A4: 3 | B4: Code Assistant | C4: Product/Engineering | D4: Coding | E4: Coding Assistance | F4: Slow delivery; rework and escaped defects; legacy migrations. | G4: 0 | H4: 800000 | I4: 0 | J4: 0 | K4: 0.8 | L4: 0.85 | M4: 2 | N4: 3 | O4: =MIN((G4*ScoringModel!$C$3+H4*ScoringModel!$C$4+I4*ScoringModel!$C$5+J4*ScoringModel!$C$6)/ScoringModel!$C$16,1) -> 0.2 | P4: =1-MIN(M4/ScoringModel!$C$17,1) -> 0.83333333 | Q4: =(N4-ScoringModel!$C$18)/(ScoringModel!$C$19-ScoringModel!$C$18) -> 0.5 | R4: =100*(ScoringModel!$C$9*O4+ScoringModel!$C$10*K4+ScoringModel!$C$11*L4+ScoringModel!$C$12*P4+ScoringModel!$C$13*(1-Q4)) -> 49.583333 | S4: =_xlfn.RANK.EQ(R4,$R$2:$R$11,0) -> 7 | T4: Lead time (days) | U4: 14 | V4: 9 | W4: 6 | X4: 80 | Y4: 10 | Z4: 1.1 | AA4: 200 | AB4: 400 | AC4: 120 | AD4: 180 | AE4: 22 | AF4: =X4*Y4*AE4*Z4*(AA4+AB4+AC4+AD4) -> 17424000
A5: 4 | B5: AP Invoice Processing | C5: Finance | D5: AP | E5: Data Analysis, Workflow Automation | F5: Manual invoice coding/3-way match; late fees; errors. | G5: 0 | H5: 500000 | I5: 2000000 | J5: 50000 | K5: 0.8 | L5: 0.9 | M5: 4 | N5: 3 | O5: =MIN((G5*ScoringModel!$C$3+H5*ScoringModel!$C$4+I5*ScoringModel!$C$5+J5*ScoringModel!$C$6)/ScoringModel!$C$16,1) -> 0.6375 | P5: =1-MIN(M5/ScoringModel!$C$17,1) -> 0.66666667 | Q5: =(N5-ScoringModel!$C$18)/(ScoringModel!$C$19-ScoringModel!$C$18) -> 0.5 | R5: =100*(ScoringModel!$C$9*O5+ScoringModel!$C$10*K5+ScoringModel!$C$11*L5+ScoringModel!$C$12*P5+ScoringModel!$C$13*(1-Q5)) -> 70.541667 | S5: =_xlfn.RANK.EQ(R5,$R$2:$R$11,0) -> 2 | T5: Invoice cycle time (days) | U5: 7 | V5: 2 | W5: 9 | X5: 6 | Y5: 240 | Z5: 1.2 | AA5: 150 | AB5: 350 | AC5: 60 | AD5: 120 | AE5: 22 | AF5: =X5*Y5*AE5*Z5*(AA5+AB5+AC5+AD5) -> 25850880
A6: 5 | B6: Predictive Maintenance | C6: Operations | D6: Maintenance | E6: Data Analysis, Workflow Automation | F6: Unplanned downtime; reactive maintenance; spare parts bloat. | G6: 0 | H6: 700000 | I6: 300000 | J6: 200000 | K6: 0.7 | L6: 0.85 | M6: 6 | N6: 4 | O6: =MIN((G6*ScoringModel!$C$3+H6*ScoringModel!$C$4+I6*ScoringModel!$C$5+J6*ScoringModel!$C$6)/ScoringModel!$C$16,1) -> 0.3 | P6: =1-MIN(M6/ScoringModel!$C$17,1) -> 0.5 | Q6: =(N6-ScoringModel!$C$18)/(ScoringModel!$C$19-ScoringModel!$C$18) -> 0.75 | R6: =100*(ScoringModel!$C$9*O6+ScoringModel!$C$10*K6+ScoringModel!$C$11*L6+ScoringModel!$C$12*P6+ScoringModel!$C$13*(1-Q6)) -> 48 | S6: =_xlfn.RANK.EQ(R6,$R$2:$R$11,0) -> 8 | T6: Unplanned downtime (hrs/yr) | U6: 1200 | V6: 800 | W6: 12 | X6: 30 | Y6: 20 | Z6: 1.3 | AA6: 120 | AB6: 300 | AC6: 80 | AD6: 120 | AE6: 22 | AF6: =X6*Y6*AE6*Z6*(AA6+AB6+AC6+AD6) -> 10639200
A7: 6 | B7: Churn Early Warning & Outreach | C7: Customer Success | D7: Renewals | E7: Data Analysis, Conversational | F7: Late churn detection; generic outreach; poor segmentation. | G7: 1200000 | H7: 0 | I7: 0 | J7: 0 | K7: 0.65 | L7: 0.8 | M7: 3 | N7: 3 | O7: =MIN((G7*ScoringModel!$C$3+H7*ScoringModel!$C$4+I7*ScoringModel!$C$5+J7*ScoringModel!$C$6)/ScoringModel!$C$16,1) -> 0.3 | P7: =1-MIN(M7/ScoringModel!$C$17,1) -> 0.75 | Q7: =(N7-ScoringModel!$C$18)/(ScoringModel!$C$19-ScoringModel!$C$18) -> 0.5 | R7: =100*(ScoringModel!$C$9*O7+ScoringModel!$C$10*K7+ScoringModel!$C$11*L7+ScoringModel!$C$12*P7+ScoringModel!$C$13*(1-Q7)) -> 50 | S7: =_xlfn.RANK.EQ(R7,$R$2:$R$11,0) -> 6 | T7: Gross revenue retention (%) | U7: 86 | V7: 90 | W7: 12 | X7: 25 | Y7: 40 | Z7: 1.2 | AA7: 250 | AB7: 500 | AC7: 120 | AD7: 220 | AE7: 22 | AF7: =X7*Y7*AE7*Z7*(AA7+AB7+AC7+AD7) -> 28776000
A8: 7 | B8: Marketing Content Studio | C8: Marketing | D8: Content | E8: Content Creation, RIR | F8: Content bottlenecks; low volume; inconsistent brand voice. | G8: 900000 | H8: 150000 | I8: 0 | J8: 0 | K8: 0.8 | L8: 0.9 | M8: 2 | N8: 2 | O8: =MIN((G8*ScoringModel!$C$3+H8*ScoringModel!$C$4+I8*ScoringModel!$C$5+J8*ScoringModel!$C$6)/ScoringModel!$C$16,1) -> 0.2625 | P8: =1-MIN(M8/ScoringModel!$C$17,1) -> 0.83333333 | Q8: =(N8-ScoringModel!$C$18)/(ScoringModel!$C$19-ScoringModel!$C$18) -> 0.25 | R8: =100*(ScoringModel!$C$9*O8+ScoringModel!$C$10*K8+ScoringModel!$C$11*L8+ScoringModel!$C$12*P8+ScoringModel!$C$13*(1-Q8)) -> 54.708333 | S8: =_xlfn.RANK.EQ(R8,$R$2:$R$11,0) -> 4 | T8: MQLs per month | U8: 1200 | V8: 1500 | W8: 6 | X8: 12 | Y8: 40 | Z8: 1.2 | AA8: 600 | AB8: 900 | AC8: 180 | AD8: 600 | AE8: 22 | AF8: =X8*Y8*AE8*Z8*(AA8+AB8+AC8+AD8) -> 28892160
A9: 8 | B9: Compliance Policy Q&A | C9: Legal/Compliance | D9: Policies | E9: RIR, Conversational | F9: Employees can't find policy answers; inconsistent interpretations. | G9: 0 | H9: 200000 | I9: 0 | J9: 750000 | K9: 0.85 | L9: 0.95 | M9: 2 | N9: 2 | O9: =MIN((G9*ScoringModel!$C$3+H9*ScoringModel!$C$4+I9*ScoringModel!$C$5+J9*ScoringModel!$C$6)/ScoringModel!$C$16,1) -> 0.2375 | P9: =1-MIN(M9/ScoringModel!$C$17,1) -> 0.83333333 | Q9: =(N9-ScoringModel!$C$18)/(ScoringModel!$C$19-ScoringModel!$C$18) -> 0.25 | R9: =100*(ScoringModel!$C$9*O9+ScoringModel!$C$10*K9+ScoringModel!$C$11*L9+ScoringModel!$C$12*P9+ScoringModel!$C$13*(1-Q9)) -> 55.208333 | S9: =_xlfn.RANK.EQ(R9,$R$2:$R$11,0) -> 3 | T9: Policy queries answered accurately (%) | U9: 60 | V9: 95 | W9: 6 | X9: 1000 | Y9: 0.2 | Z9: 1.1 | AA9: 120 | AB9: 280 | AC9: 60 | AD9: 100 | AE9: 22 | AF9: =X9*Y9*AE9*Z9*(AA9+AB9+AC9+AD9) -> 2710400
A10: 9 | B10: Field Service Route & Remedy Copilot | C10: Operations | D10: Dispatch | E10: Conversational, Workflow Automation | F10: Inefficient routing; repeat truck rolls; tribal knowledge. | G10: 0 | H10: 650000 | I10: 0 | J10: 100000 | K10: 0.75 | L10: 0.85 | M10: 4 | N10: 3 | O10: =MIN((G10*ScoringModel!$C$3+H10*ScoringModel!$C$4+I10*ScoringModel!$C$5+J10*ScoringModel!$C$6)/ScoringModel!$C$16,1) -> 0.1875 | P10: =1-MIN(M10/ScoringModel!$C$17,1) -> 0.66666667 | Q10: =(N10-ScoringModel!$C$18)/(ScoringModel!$C$19-ScoringModel!$C$18) -> 0.5 | R10: =100*(ScoringModel!$C$9*O10+ScoringModel!$C$10*K10+ScoringModel!$C$11*L10+ScoringModel!$C$12*P10+ScoringModel!$C$13*(1-Q10)) -> 46.291667 | S10: =_xlfn.RANK.EQ(R10,$R$2:$R$11,0) -> 9 | T10: Repeat visits (%) | U10: 18 | V10: 10 | W10: 9 | X10: 50 | Y10: 25 | Z10: 1.2 | AA10: 200 | AB10: 500 | AC10: 120 | AD10: 150 | AE10: 22 | AF10: =X10*Y10*AE10*Z10*(AA10+AB10+AC10+AD10) -> 32010000
A11: 10 | B11: Talent Onboarding Copilot | C11: HR/People | D11: Onboarding | E11: Conversational, RIR | F11: Slow time-to-productivity; inconsistent onboarding; high ticket volume. | G11: 0 | H11: 250000 | I11: 0 | J11: 0 | K11: 0.8 | L11: 0.8 | M11: 2 | N11: 2 | O11: =MIN((G11*ScoringModel!$C$3+H11*ScoringModel!$C$4+I11*ScoringModel!$C$5+J11*ScoringModel!$C$6)/ScoringModel!$C$16,1) -> 0.0625 | P11: =1-MIN(M11/ScoringModel!$C$17,1) -> 0.83333333 | Q11: =(N11-ScoringModel!$C$18)/(ScoringModel!$C$19-ScoringModel!$C$18) -> 0.25 | R11: =100*(ScoringModel!$C$9*O11+ScoringModel!$C$10*K11+ScoringModel!$C$11*L11+ScoringModel!$C$12*P11+ScoringModel!$C$13*(1-Q11)) -> 43.208333 | S11: =_xlfn.RANK.EQ(R11,$R$2:$R$11,0) -> 10 | T11: Time to productivity (days) | U11: 60 | V11: 45 | W11: 6 | X11: 100 | Y11: 3 | Z11: 1.1 | AA11: 250 | AB11: 400 | AC11: 80 | AD11: 200 | AE11: 22 | AF11: =X11*Y11*AE11*Z11*(AA11+AB11+AC11+AD11) -> 6751800

Sheet TokenModel
A1: Primitive | B1: Typical Input | C1: Typical Processing | D1: Typical Reasoning | E1: Typical Output | G1: Guidance
A2: Content Creation | B2: 800 | C2: 600 | D2: 200 | E2: 800 | G2: Use these as starting points; override per use case in Backlog. ToolCallsPerPrompt captures multi-tool/agent hops. DaysPerMonth defaults to 22.
A3: Research & Info Retrieval | B3: 300 | C3: 900 | D3: 150 | E3: 300
A4: Coding Assistance | B4: 150 | C4: 300 | D4: 120 | E4: 180
A5: Data Analysis | B5: 250 | C5: 600 | D5: 180 | E5: 220
A6: Conversational Interfaces | B6: 120 | C6: 280 | D6: 60 | E6: 150
A7: Workflow Automation | B7: 180 | C7: 500 | D7: 120 | E7: 150

Sheet Roadmap_Snapshot
A1: ID | B1: UseCase | C1: Function | D1: SubFunction | E1: Primitives | F1: RevBenefitUSD | G1: CostBenefitUSD | H1: CashFlowBenefitUSD | I1: RiskBenefitUSD | J1: Psuccess | K1: Alignment | L1: TTV_Months | M1: EffortScore | N1: PriorityScore | O1: MonthlyTokens_Est
A2: 1 | B2: Sales Proposal Generator | C2: Sales | D2: Proposal/Bid | E2: Content Creation, RIR, Conversational | F2: 2500000 | G2: 300000 | H2: 0 | I2: 0 | J2: 0.75 | K2: 0.95 | L2: 3 | M2: 3 | N2: 74.25 | O2: 56284800
A3: 4 | B3: AP Invoice Processing | C3: Finance | D3: AP | E3: Data Analysis, Workflow Automation | F3: 0 | G3: 500000 | H3: 2000000 | I3: 50000 | J3: 0.8 | K3: 0.9 | L3: 4 | M3: 3 | N3: 70.541667 | O3: 25850880
A4: 8 | B4: Compliance Policy Q&A | C4: Legal/Compliance | D4: Policies | E4: RIR, Conversational | F4: 0 | G4: 200000 | H4: 0 | I4: 750000 | J4: 0.85 | K4: 0.95 | L4: 2 | M4: 2 | N4: 55.208333 | O4: 2710400
A5: 7 | B5: Marketing Content Studio | C5: Marketing | D5: Content | E5: Content Creation, RIR | F5: 900000 | G5: 150000 | H5: 0 | I5: 0 | J5: 0.8 | K5: 0.9 | L5: 2 | M5: 2 | N5: 54.708333 | O5: 28892160
A6: 2 | B6: Helpdesk Copilot (IT/HR) | C6: IT | D6: Helpdesk | E6: Conversational, RIR, Workflow Automation | F6: 0 | G6: 600000 | H6: 0 | I6: 100000 | J6: 0.85 | K6: 0.9 | L6: 2 | M6: 2 | N6: 51.333333 | O6: 14784000
A7: 6 | B7: Churn Early Warning & Outreach | C7: Customer Success | D7: Renewals | E7: Data Analysis, Conversational | F7: 1200000 | G7: 0 | H7: 0 | I7: 0 | J7: 0.65 | K7: 0.8 | L7: 3 | M7: 3 | N7: 50 | O7: 28776000
A8: 3 | B8: Code Assistant | C8: Product/Engineering | D8: Coding | E8: Coding Assistance | F8: 0 | G8: 800000 | H8: 0 | I8: 0 | J8: 0.8 | K8: 0.85 | L8: 2 | M8: 3 | N8: 49.583333 | O8: 17424000
A9: 5 | B9: Predictive Maintenance | C9: Operations | D9: Maintenance | E9: Data Analysis, Workflow Automation | F9: 0 | G9: 700000 | H9: 300000 | I9: 200000 | J9: 0.7 | K9: 0.85 | L9: 6 | M9: 4 | N9: 48 | O9: 10639200
A10: 9 | B10: Field Service Route & Remedy Copilot | C10: Operations | D10: Dispatch | E10: Conversational, Workflow Automation | F10: 0 | G10: 650000 | H10: 0 | I10: 100000 | J10: 0.75 | K10: 0.85 | L10: 4 | M10: 3 | N10: 46.291667 | O10: 32010000
A11: 10 | B11: Talent Onboarding Copilot | C11: HR/People | D11: Onboarding | E11: Conversational, RIR | F11: 0 | G11: 250000 | H11: 0 | I11: 0 | J11: 0.8 | K11: 0.8 | L11: 2 | M11: 2 | N11: 43.208333 | O11: 6751800

Sheet ExecutiveDashboard
A1: AI Portfolio – Executive Dashboard
A2: Live metrics linked to Backlog (edit weights in ScoringModel; tokens in Backlog).
A4: Key Totals | D4: Top 5 Use Cases by Priority
A6: Total Annual Revenue Benefit | B6: =SUM('Use Cases'!G2:G11) -> 4600000 | D6: Rank | E6: UseCase | F6: PriorityScore | G6: Monthly Tokens | H6: Annual Value ($)
A7: Total Annual Cost Benefit | B7: =SUM('Use Cases'!H2:H11) -> 4150000 | D7: 1 | E7: =INDEX('Use Cases'!$B$2:$B$11, I7) -> Sales Proposal Generator | F7: =INDEX('Use Cases'!$R$2:$R$11, I7) -> 74.25 | G7: =INDEX('Use Cases'!$AF$2:$AF$11, I7) -> 56284800 | H7: =INDEX('Use Cases'!$G$2:$G$11, I7)+INDEX('Use Cases'!$H$2:$H$11, I7)+INDEX('Use Cases'!$I$2:$I$11, I7)+INDEX('Use Cases'!$J$2:$J$11, I7) -> 2800000 | I7: =MATCH(D7,'Use Cases'!$S$2:$S$11,0) -> 1
A8: Total Annual Cash Flow Benefit | B8: =SUM('Use Cases'!I2:I11) -> 2300000 | D8: 2 | E8: =INDEX('Use Cases'!$B$2:$B$11, I8) -> AP Invoice Processing | F8: =INDEX('Use Cases'!$R$2:$R$11, I8) -> 70.541667 | G8: =INDEX('Use Cases'!$AF$2:$AF$11, I8) -> 25850880 | H8: =INDEX('Use Cases'!$G$2:$G$11, I8)+INDEX('Use Cases'!$H$2:$H$11, I8)+INDEX('Use Cases'!$I$2:$I$11, I8)+INDEX('Use Cases'!$J$2:$J$11, I8) -> 2550000 | I8: =MATCH(D8,'Use Cases'!$S$2:$S$11,0) -> 4
A9: Total Annual Risk Benefit | B9: =SUM('Use Cases'!J2:J11) -> 1200000 | D9: 3 | E9: =INDEX('Use Cases'!$B$2:$B$11, I9) -> Compliance Policy Q&A | F9: =INDEX('Use Cases'!$R$2:$R$11, I9) -> 55.208333 | G9: =INDEX('Use Cases'!$AF$2:$AF$11, I9) -> 2710400 | H9: =INDEX('Use Cases'!$G$2:$G$11, I9)+INDEX('Use Cases'!$H$2:$H$11, I9)+INDEX('Use Cases'!$I$2:$I$11, I9)+INDEX('Use Cases'!$J$2:$J$11, I9) -> 950000 | I9: =MATCH(D9,'Use Cases'!$S$2:$S$11,0) -> 8
A10: Total Annual Value (All Drivers) | B10: =B6+B7+B8+B9 -> 12250000 | D10: 4 | E10: =INDEX('Use Cases'!$B$2:$B$11, I10) -> Marketing Content Studio | F10: =INDEX('Use Cases'!$R$2:$R$11, I10) -> 54.708333 | G10: =INDEX('Use Cases'!$AF$2:$AF$11, I10) -> 28892160 | H10: =INDEX('Use Cases'!$G$2:$G$11, I10)+INDEX('Use Cases'!$H$2:$H$11, I10)+INDEX('Use Cases'!$I$2:$I$11, I10)+INDEX('Use Cases'!$J$2:$J$11, I10) -> 1050000 | I10: =MATCH(D10,'Use Cases'!$S$2:$S$11,0) -> 7
D11: 5 | E11: =INDEX('Use Cases'!$B$2:$B$11, I11) -> Helpdesk Copilot (IT/HR) | F11: =INDEX('Use Cases'!$R$2:$R$11, I11) -> 51.333333 | G11: =INDEX('Use Cases'!$AF$2:$AF$11, I11) -> 14784000 | H11: =INDEX('Use Cases'!$G$2:$G$11, I11)+INDEX('Use Cases'!$H$2:$H$11, I11)+INDEX('Use Cases'!$I$2:$I$11, I11)+INDEX('Use Cases'!$J$2:$J$11, I11) -> 700000 | I11: =MATCH(D11,'Use Cases'!$S$2:$S$11,0) -> 2
A12: Total Monthly Tokens (All Use Cases) | B12: =SUM('Use Cases'!AF2:AF11) -> 224123240
A13: Value per 1M Tokens (Annualized) | B13: =IF(B12>0, B10/(B12*12/1000000), "") -> 4554.7857
